flasynk/__init__.py
flasynk/_asynchronous.py
flasynk/celery_mock.py
flasynk/celery_specifics.py
flasynk/huey_specifics.py
flasynk/version.py
flasynk-1.5.0.dist-info/LICENSE
flasynk-1.5.0.dist-info/METADATA
flasynk-1.5.0.dist-info/WHEEL
flasynk-1.5.0.dist-info/top_level.txt
flasynk-1.5.0.dist-info/RECORD
