Metadata-Version: 2.1
Name: flasynk
Version: 1.5.0
Summary: Exposing Asynchronous endpoint using Flask-RestPlus
Home-page: https://colin-b.github.io/flasynk/
Author: Colin Bounouar
Author-email: colin.bounouar.dev@gmail.com
Maintainer: Colin Bounouar
Maintainer-email: colin.bounouar.dev@gmail.com
License: MIT
Download-URL: https://pypi.org/project/flasynk/
Project-URL: GitHub, https://github.com/Colin-b/flasynk
Project-URL: Changelog, https://github.com/Colin-b/flasynk/blob/master/CHANGELOG.md
Project-URL: Issues, https://github.com/Colin-b/flasynk/issues
Keywords: async,asynchronous,rest,flask
Platform: Windows
Platform: Linux
Classifier: Development Status :: 5 - Production/Stable
Classifier: Intended Audience :: Developers
Classifier: License :: OSI Approved :: MIT License
Classifier: Natural Language :: English
Classifier: Programming Language :: Python
Classifier: Programming Language :: Python :: 3
Classifier: Programming Language :: Python :: 3.6
Classifier: Programming Language :: Python :: 3.7
Classifier: Programming Language :: Python :: 3.8
Classifier: Topic :: Software Development :: Build Tools
Requires-Python: >=3.7
Requires-Dist: flask-restplus (==0.13.*)
Provides-Extra: celery
Requires-Dist: celery[msgpack,redis] (==4.*) ; extra == 'celery'
Provides-Extra: huey
Requires-Dist: huey (==2.*) ; extra == 'huey'
Requires-Dist: redis (==3.*) ; extra == 'huey'
Provides-Extra: testing
Requires-Dist: celery[msgpack,redis] (==4.*) ; extra == 'testing'
Requires-Dist: huey (==2.*) ; extra == 'testing'
Requires-Dist: pytest-flask (==0.15.*) ; extra == 'testing'
Requires-Dist: pytest-cov (==2.*) ; extra == 'testing'
